dldb/__init__.py
dldb/dldb.py
dldb/preprocessor.py
dldb-0.0.2.dist-info/DESCRIPTION.rst
dldb-0.0.2.dist-info/METADATA
dldb-0.0.2.dist-info/RECORD
dldb-0.0.2.dist-info/WHEEL
dldb-0.0.2.dist-info/metadata.json
dldb-0.0.2.dist-info/top_level.txt
