Metadata-Version: 2.0
Name: dldb
Version: 0.0.2
Summary: Deep learning for relational datasets with a time-component
Home-page: https://github.com/HDI-Project/DL-DB
License: UNKNOWN
Platform: UNKNOWN
Requires-Python: >=3
Requires-Dist: featuretools (>=0.1.20)
Requires-Dist: keras (>=2.1.4)
Requires-Dist: scikit-learn (>=0.19.1)
Requires-Dist: tensorflow (>=1.6.0)
